setup.py
src/TheLoadOfTheLoad.egg-info/PKG-INFO
src/TheLoadOfTheLoad.egg-info/SOURCES.txt
src/TheLoadOfTheLoad.egg-info/dependency_links.txt
src/TheLoadOfTheLoad.egg-info/requires.txt
src/TheLoadOfTheLoad.egg-info/top_level.txt
src/lol/__init__.py
src/lol/database.py
src/lol/databaseconfig.py
src/lol/dataconfig.py
src/lol/datafile.py
src/lol/loader.py
src/lol/lol.py
src/lol/mysql.py
src/lol/sqlite.py