Metadata-Version: 1.0
Name: TheLoadOfTheLoad
Version: 0.1.0
Summary: Load csv file into the database table.
Home-page: UNKNOWN
Author: Hiroaki Nagashima
Author-email: cr9h-ngsm@asahi-net.or.jp
License: Copyright (C) 2009 Hiroaki Nagashima. All rights reserved. Freely distributable and usable for non-commercial
Keywords: csv database
Platform: UNKNOWN
